{
  "fn-track": {
    "per-service-total": {
      "play-store-app": 469454
    },
    "total": 469454
  },
  "mc-anticheat": {
    "per-service-total": {
      "modrinth-mod": 3023
    },
    "total": 3023
  },
  "mc-autototem": {
    "per-service-total": {
      "modrinth-mod": 297286
    },
    "total": 297286
  },
  "mc-clear-enchanting": {
    "per-service-total": {
      "modrinth-mod": 6406
    },
    "total": 6406
  },
  "mc-torch": {
    "per-service-total": {
      "modrinth-mod": 6138
    },
    "total": 6138
  },
  "obsidian-advanced-canvas": {
    "per-service-total": {
      "obsidian-plugin": 238580
    },
    "total": 238580
  },
  "obsidian-calctex": {
    "per-service-total": {
      "obsidian-plugin": 6343
    },
    "total": 6343
  },
  "obsidian-docxer": {
    "per-service-total": {
      "obsidian-plugin": 28937
    },
    "total": 28937
  },
  "what": {
    "per-service-total": {
      "play-store-app": 78
    },
    "total": 78
  }
}