{
  "fn-track": {
    "per-service-total": {
      "play-store-app": 600042
    },
    "total": 600042
  },
  "mc-anticheat": {
    "per-service-total": {
      "modrinth-mod": 5724
    },
    "total": 5724
  },
  "mc-autototem": {
    "per-service-total": {
      "curseforge-mod": 67765,
      "modrinth-mod": 618619
    },
    "total": 686384
  },
  "mc-clear-enchanting": {
    "per-service-total": {
      "modrinth-mod": 7807
    },
    "total": 7807
  },
  "mc-torch": {
    "per-service-total": {
      "modrinth-mod": 10488
    },
    "total": 10488
  },
  "obsidian-advanced-canvas": {
    "per-service-total": {
      "obsidian-plugin": 612633
    },
    "total": 612633
  },
  "obsidian-calctex": {
    "per-service-total": {
      "obsidian-plugin": 9098
    },
    "total": 9098
  },
  "obsidian-docxer": {
    "per-service-total": {
      "obsidian-plugin": 81924
    },
    "total": 81924
  },
  "starlight-pdf": {
    "per-service-total": {
      "github-release": 461
    },
    "total": 461
  },
  "what": {
    "per-service-total": {
      "play-store-app": 98
    },
    "total": 98
  }
}