{
  "fn-track": {
    "per-service-total": {
      "play-store-app": 587559
    },
    "total": 587559
  },
  "mc-anticheat": {
    "per-service-total": {
      "modrinth-mod": 4765
    },
    "total": 4765
  },
  "mc-autototem": {
    "per-service-total": {
      "curseforge-mod": 31087,
      "modrinth-mod": 515500
    },
    "total": 546587
  },
  "mc-clear-enchanting": {
    "per-service-total": {
      "modrinth-mod": 7451
    },
    "total": 7451
  },
  "mc-torch": {
    "per-service-total": {
      "modrinth-mod": 9791
    },
    "total": 9791
  },
  "obsidian-advanced-canvas": {
    "per-service-total": {
      "obsidian-plugin": 496509
    },
    "total": 496509
  },
  "obsidian-calctex": {
    "per-service-total": {
      "obsidian-plugin": 8224
    },
    "total": 8224
  },
  "obsidian-docxer": {
    "per-service-total": {
      "obsidian-plugin": 57929
    },
    "total": 57929
  },
  "starlight-pdf": {
    "per-service-total": {
      "github-release": 411
    },
    "total": 411
  },
  "what": {
    "per-service-total": {
      "play-store-app": 87
    },
    "total": 87
  }
}