{
  "fn-track": {
    "per-service-total": {
      "play-store-app": 473527
    },
    "total": 473527
  },
  "mc-anticheat": {
    "per-service-total": {
      "modrinth-mod": 3249
    },
    "total": 3249
  },
  "mc-autototem": {
    "per-service-total": {
      "modrinth-mod": 323147
    },
    "total": 323147
  },
  "mc-clear-enchanting": {
    "per-service-total": {
      "modrinth-mod": 6563
    },
    "total": 6563
  },
  "mc-torch": {
    "per-service-total": {
      "modrinth-mod": 6478
    },
    "total": 6478
  },
  "obsidian-advanced-canvas": {
    "per-service-total": {
      "obsidian-plugin": 266685
    },
    "total": 266685
  },
  "obsidian-calctex": {
    "per-service-total": {
      "obsidian-plugin": 6478
    },
    "total": 6478
  },
  "obsidian-docxer": {
    "per-service-total": {
      "obsidian-plugin": 30926
    },
    "total": 30926
  },
  "what": {
    "per-service-total": {
      "play-store-app": 78
    },
    "total": 78
  }
}