{
  "fn-track": {
    "per-service-total": {
      "play-store-app": 464942
    },
    "total": 464942
  },
  "mc-anticheat": {
    "per-service-total": {
      "modrinth-mod": 2543
    },
    "total": 2543
  },
  "mc-autototem": {
    "per-service-total": {
      "modrinth-mod": 269263
    },
    "total": 269263
  },
  "mc-clear-enchanting": {
    "per-service-total": {
      "modrinth-mod": 6246
    },
    "total": 6246
  },
  "mc-torch": {
    "per-service-total": {
      "modrinth-mod": 5817
    },
    "total": 5817
  },
  "obsidian-advanced-canvas": {
    "per-service-total": {
      "obsidian-plugin": 211029
    },
    "total": 211029
  },
  "obsidian-calctex": {
    "per-service-total": {
      "obsidian-plugin": 6136
    },
    "total": 6136
  },
  "obsidian-docxer": {
    "per-service-total": {
      "obsidian-plugin": 26835
    },
    "total": 26835
  },
  "what": {
    "per-service-total": {
      "play-store-app": 77
    },
    "total": 77
  }
}