{
  "fn-track": {
    "per-service-total": {
      "play-store-app": 484524
    },
    "total": 484524
  },
  "mc-anticheat": {
    "per-service-total": {
      "modrinth-mod": 3731
    },
    "total": 3731
  },
  "mc-autototem": {
    "per-service-total": {
      "modrinth-mod": 374454
    },
    "total": 374454
  },
  "mc-clear-enchanting": {
    "per-service-total": {
      "modrinth-mod": 6918
    },
    "total": 6918
  },
  "mc-torch": {
    "per-service-total": {
      "modrinth-mod": 7397
    },
    "total": 7397
  },
  "obsidian-advanced-canvas": {
    "per-service-total": {
      "obsidian-plugin": 359600
    },
    "total": 359600
  },
  "obsidian-calctex": {
    "per-service-total": {
      "obsidian-plugin": 7076
    },
    "total": 7076
  },
  "obsidian-docxer": {
    "per-service-total": {
      "obsidian-plugin": 41764
    },
    "total": 41764
  },
  "what": {
    "per-service-total": {
      "play-store-app": 83
    },
    "total": 83
  }
}